{"title":"Rousseau's Revolution and the Authentic Self","markdown":{"headingText":"Rousseau's Revolution and the Authentic Self","containsRefs":false,"markdown":"\nJean-Jacques Rousseau occupies a unique and pivotal position in our intellectual history—he was simultaneously the last great thinker of the Enlightenment and the first great critic of Enlightenment rationalism, the most systematic defender of human natural goodness and the most penetrating analyst of how civilization corrupts that goodness, the theorist of democratic self-government and the prophet of totalitarian democracy. His influence on subsequent thinking about authenticity, self-expression, and individual freedom has been so profound that it is difficult to imagine modern culture without it. Yet his ideas also contained tensions and contradictions that would generate many of the deepest problems of modern political and moral life.\n\nWhat made Rousseau revolutionary was not simply his critique of existing social arrangements—many Enlightenment thinkers had done that—but his fundamental challenge to the assumptions about human nature and moral development that had guided Western thinking since antiquity. Where earlier thinkers had generally assumed that civilization represented progress from a primitive state of nature, Rousseau argued that it represented decline from an original condition of innocence and natural virtue. Where they had seen reason and social refinement as sources of human improvement, he saw them as sources of corruption and alienation. Where they had sought to perfect human nature through education and institutional reform, he sought to recover a more authentic way of being that had been lost through the very process of social development.\n\nThis Rousseauian revolution in thinking about human nature and social development would prove enormously influential for later movements—Romanticism, nationalism, socialism, existentialism—that emphasized feeling over reason, authenticity over convention, and individual expression over social conformity. But it would also create new forms of moral and political confusion that earlier traditions had been better equipped to handle. The tension between Rousseau's democratic idealism and his authoritarian implications, between his celebration of natural innocence and his recognition of social necessity, between his individualistic psychology and his collectivistic politics, would continue to generate creative and destructive possibilities in subsequent intellectual and political history.\n\n## The Critique of Civilization: Natural Goodness and Social Corruption\n\nRousseau's intellectual journey began with a profound moral crisis triggered by his reading of the question posed by the Academy of Dijon in 1749: \"Has the progress of the sciences and arts contributed to the purification of morals?\" His negative answer, developed in his *Discourse on the Sciences and Arts*, challenged one of the fundamental assumptions of Enlightenment culture—that knowledge, refinement, and social sophistication represented unambiguous goods that contributed to human happiness and moral improvement.\n\nRousseau argued instead that the development of arts and sciences had coincided with moral decline rather than moral progress. Ancient peoples like the Spartans and early Romans had been virtuous precisely because they were simple and uncorrupted by luxury, learning, and social refinement. Modern Europeans, despite their superior knowledge and technical achievements, were morally inferior—more selfish, more artificial, more concerned with appearance than reality, more willing to sacrifice genuine virtue for social approval and material advantage.\n\nThis critique of civilization was developed more systematically in Rousseau's *Discourse on the Origin of Inequality*, which attempted to trace the historical process by which natural human goodness had been corrupted by social development. In the state of nature, Rousseau argued, human beings had been naturally compassionate, free from the artificial needs created by social comparison, and innocent of the vices that emerged from property, inequality, and competitive social relations. The establishment of private property—\"the first man who, having enclosed a piece of ground, bethought himself of saying 'This is mine,' and found people simple enough to believe him\"—was the crucial step that led to all subsequent forms of inequality, conflict, and moral corruption.\n\nRousseau's account of natural goodness was more psychologically sophisticated than either the Christian doctrine of original sin or the Hobbesian account of natural selfishness. He distinguished between *amour de soi* (natural self-love) and *amour-propre* (social self-esteem), arguing that the former was a healthy and necessary aspect of human nature while the latter was an artificial creation of social life that led to vanity, envy, and cruelty. Natural human beings cared for their own survival and well-being, but they did not need to compare themselves with others or derive their sense of worth from social recognition.\n\nThe implications of this analysis were radical. If human beings were naturally good and had been corrupted by social institutions, then moral and political reform required not the improvement of such institutions but their fundamental transformation or elimination. If inequality and competition were the sources of human vice, then justice required the creation of social arrangements that minimized both. If authentic virtue was natural rather than learned, then moral education should focus on protecting and nurturing innate goodness rather than imposing external standards of behavior.\n\nBut Rousseau's critique of civilization also created obvious difficulties. If social development inevitably led to corruption, how could any form of organized social life be legitimate? If natural goodness was lost through the development of reason and culture, how could rational argument or cultural reform restore it? If inequality and competition were inherent in any complex society, how could the values of natural simplicity be preserved without abandoning the achievements of civilization that made life longer, safer, and more materially comfortable?\n\n## Émile and the Education of Natural Man\n\nRousseau's attempt to resolve these difficulties took the form of an educational treatise, *Émile*, which described how a child might be raised to preserve his natural goodness while acquiring the knowledge and skills necessary for life in civilized society. This was perhaps Rousseau's most influential work, and it represented a revolutionary approach to thinking about human development, individual autonomy, and the relationship between nature and culture.\n\nThe central principle of Rousseauian education was that the child's natural development should be allowed to unfold according to its own internal logic rather than being forced into artificial patterns imposed by adult authority. \"Everything is good as it leaves the hands of the Author of things; everything degenerates in the hands of man,\" Rousseau declared, meaning that education should protect rather than reform human nature. The teacher's role was not to impose knowledge or values but to create conditions where natural learning could occur and natural virtue could flourish.\n\nThis approach to education had profound implications for thinking about individual autonomy and authentic self-development. If genuine learning required internal motivation rather than external compulsion, then true education must be based on the student's own curiosity and interest rather than on predetermined curricula or authoritative instruction. If natural development followed its own pattern, then individual differences in temperament, ability, and inclination must be respected rather than forced into conformity with social expectations.\n\nRousseau's educational psychology also emphasized the importance of direct experience and emotional engagement over abstract reasoning and verbal instruction. Émile would learn about the natural world through direct observation and experimentation rather than through books and lectures. He would develop moral sentiments through exposure to the consequences of his actions rather than through moral exhortation. He would acquire social skills through genuine relationships rather than through formal instruction in manners and etiquette.\n\nThis Rousseauian approach to education represented a fundamental challenge to both classical and Christian traditions that had emphasized the importance of disciplining natural inclinations according to rational or revealed standards of excellence. Where Aristotelian education sought to habituate students in virtuous practices through repeated action, Rousseauian education sought to protect natural virtue from artificial corruption. Where Christian education sought to correct the effects of original sin through moral instruction and spiritual discipline, Rousseauian education sought to preserve original innocence through careful environmental management.\n\nThe political implications of this educational philosophy were significant. If individuals who had been properly educated according to natural principles would be genuinely autonomous—capable of thinking and choosing for themselves without dependence on external authority—then democratic self-government became not merely possible but necessary. A society of naturally educated citizens would not need the hierarchical authority structures that were required to govern people whose natural capacities had been corrupted by conventional education.\n\nBut Rousseau's educational ideal also contained authoritarian potentials that he did not fully acknowledge. If natural development required careful environmental control, then the educator would need enormous power over the student's experience. If natural learning was superior to conventional instruction, then those who understood natural principles would be justified in rejecting the preferences and judgments of those who had been corrupted by conventional education. If authentic autonomy was achievable only through proper education, then those who had not received such education might legitimately be forced to be free.\n\n## The Social Contract: Forcing Men to Be Free\n\nRousseau's political philosophy, developed in *The Social Contract*, represented his most systematic attempt to reconcile individual freedom with social authority, natural goodness with political necessity, democratic equality with effective government. His famous opening declaration—\"Man is born free, and everywhere he is in chains\"—expressed his conviction that existing political arrangements were fundamentally illegitimate but that some form of social organization was necessary for human flourishing.\n\nThe solution Rousseau proposed was the creation of political communities based on what he called the \"general will\"—the collective judgment of the entire citizenry about what served the common good. When individuals participated in forming the general will, they were not submitting to external authority but rather expressing their own deepest and most rational desires as members of a political community. True freedom consisted not in doing whatever one wanted but in willing what was genuinely good for oneself as part of a larger whole.\n\nThis conception of democratic freedom was both more demanding and more transformative than earlier contractarian theories. Where Hobbes had sought to create artificial authority that could impose order on naturally selfish individuals, and Locke had sought to protect natural rights through limited government, Rousseau sought to create moral community that would transform selfish individuals into virtuous citizens. Political participation was not merely a means of protecting individual interests but a form of moral education that would develop capacities for public-spiritedness and rational self-government.\n\nRousseau's concept of the general will was designed to resolve the traditional tension between individual freedom and political authority. When citizens obeyed laws that expressed the general will, they were obeying themselves rather than external masters. When they were compelled to conform to the general will against their immediate inclinations, they were being \"forced to be free\"—compelled to act on their own best interests as rational members of a political community rather than as selfish private individuals.\n\nBut this Rousseauian solution to the problem of political obligation created new difficulties about the relationship between individual autonomy and collective authority. If the general will was always right, what happened when individual citizens believed that particular laws or policies violated their moral convictions? If democratic participation was supposed to transform private interest into public spirit, what guaranteed that such transformation would actually occur? If political communities were supposed to generate genuine unanimity about the common good, how could disagreement and dissent be accommodated without undermining the legitimacy of collective decisions?\n\nRousseau's own answers to these questions were often ambiguous and sometimes disturbing. He suggested that those who refused to conform to the general will had demonstrated that they were not really members of the political community and could legitimately be excluded or compelled to comply. He argued that genuine citizens would naturally agree about fundamental questions because their participation in democratic deliberation would purify their motives and clarify their reasoning. He proposed various institutional mechanisms—civil religion, censorship, sumptuary laws—that would maintain the moral and cultural unity necessary for democratic self-government.\n\nThese authoritarian implications of Rousseauian democracy would prove enormously controversial and would be invoked by both defenders and critics of later totalitarian movements. The idea that true freedom required conformity to the rational will of the community, that individual dissent reflected selfishness or confusion rather than legitimate disagreement, and that democratic government could legitimately use extensive powers to shape the character and culture of citizens—all these ideas contained potentials for tyranny that liberal critics would find deeply troubling.\n\n## The Religion of Natural Sentiment\n\nRousseau's critique of conventional religion paralleled his critique of conventional morality and politics. Just as social institutions had corrupted natural virtue, and just as artificial education had corrupted natural learning, so conventional theology had corrupted natural religious sentiment. The elaborate doctrinal systems, institutional hierarchies, and ritual practices of organized religion had obscured rather than clarified the simple truths that any sincere person could discover through immediate experience and natural reflection.\n\nIn the \"Profession of Faith of the Savoyard Vicar,\" included in *Émile*, Rousseau articulated a natural religion based on sentiment rather than reason, individual experience rather than institutional authority, and universal moral principles rather than particular historical revelations. The existence of God could be known through the order and beauty of the natural world, the immortality of the soul through the natural human longing for justice and meaning, and the content of moral obligation through the natural human capacity for conscience and sympathy.\n\nThis Rousseauian approach to religion was simultaneously more individualistic and more universalistic than traditional Christianity. It was more individualistic because it located religious authority in the immediate experience of each believer rather than in church teaching or biblical revelation. It was more universalistic because it suggested that the essential truths of religion were accessible to all human beings regardless of their cultural background or historical circumstances.\n\nThe political implications of this natural religion were significant. If genuine religious truth was universal and accessible to natural reason and sentiment, then religious diversity and conflict reflected the corruption of natural religion by artificial theology rather than genuine disagreement about ultimate questions. If true religion consisted in universal moral principles rather than particular historical claims, then political communities could be unified around shared moral commitments without requiring agreement about disputed theological doctrines.\n\nBut Rousseau's natural religion also created new difficulties for thinking about the relationship between religious belief and political authority. If religious truth was individual and immediate, how could shared religious commitments be maintained in political communities? If natural religion was universal, why did different individuals and cultures develop such different religious practices and beliefs? If moral conscience was the foundation of both religious and political obligation, what happened when the two conflicted?\n\nRousseau's proposed solution was the establishment of a \"civil religion\" that would combine the social benefits of shared religious commitment with the rational accessibility of natural theology. Citizens would be required to affirm belief in God, divine providence, the afterlife, and the moral law, but they would not be required to accept any particular theological system or to participate in any specific religious practices. This civil religion would provide the moral foundation necessary for political community without creating the sectarian divisions that had plagued European politics for centuries.\n\nThis Rousseauian approach to civil religion would prove influential for later attempts to combine religious and political authority, but it would also reveal the difficulty of maintaining genuine religious commitment on such minimal foundations. The reduction of religion to its supposedly essential moral core seemed to many critics to eliminate precisely what made religion valuable—its capacity to address ultimate questions about meaning and purpose that could not be resolved through moral reasoning alone.\n\n## The Birth of Romanticism: Feeling as a Guide to Truth\n\nRousseau's elevation of sentiment over reason, nature over convention, and individual experience over social authority would prove enormously influential for the Romantic movement that emerged in the late eighteenth and early nineteenth centuries. His *Confessions*, which presented an unprecedented exploration of individual psychological development and emotional experience, provided a model for the Romantic emphasis on subjective experience and personal authenticity.\n\nThe Rousseauian insight that genuine truth was more likely to be found in immediate feeling than in abstract reasoning challenged the fundamental assumptions of Enlightenment rationalism. If the natural human heart was a more reliable guide than educated intellect, then ordinary people might have better access to moral and religious truth than learned elites. If spontaneous emotion was more authentic than disciplined reflection, then the cultivation of feeling might be more important than the development of rational capacity.\n\nThis Romantic transformation of Rousseauian insights created new possibilities for individual self-expression and cultural creativity. The emphasis on originality, personal vision, and emotional intensity encouraged artistic and literary innovations that would not have been possible within more conventional frameworks. The celebration of individual difference and subjective experience provided resources for challenging social conformity and institutional authority that had been less available to earlier generations.\n\nBut the Romantic appropriation of Rousseauian themes also created new forms of moral and intellectual confusion. If feeling was superior to reason as a guide to truth, how could disagreements between different feelings be resolved? If individual authenticity was the highest value, what happened to shared moral standards and social cooperation? If originality and self-expression were intrinsically valuable, what prevented the collapse into narcissism and self-indulgence?\n\nThe Romantic legacy of Rousseauian thought would prove particularly influential for later thinking about individual freedom and self-realization. The idea that each person possessed a unique inner nature that demanded expression, that social conventions and institutional authorities were obstacles to authentic self-development, and that genuine virtue consisted in being true to oneself rather than conforming to external standards—all these ideas became central to modern individualistic culture.\n\n## The Contradictions of Rousseauian Freedom\n\nRousseau's revolutionary approach to thinking about human nature, education, politics, and religion contained tensions and contradictions that he never fully resolved and that would continue to generate problems for later thinkers influenced by his ideas. The fundamental contradiction was between his individualistic psychology and his collectivistic politics—between his celebration of natural individual autonomy and his insistence on the need for social unity and collective authority.\n\nOn the one hand, Rousseau insisted that individuals were naturally free, that genuine education must respect individual development, and that authentic virtue consisted in being true to one's natural sentiments rather than conforming to social expectations. This individualistic strand of his thought pointed toward conclusions about personal autonomy and self-expression that would prove enormously influential for later liberal and libertarian movements.\n\nOn the other hand, Rousseau also insisted that individual freedom was meaningless without political community, that genuine education required careful social control of the child's environment, and that authentic virtue was impossible without collective commitment to the common good. This collectivistic strand of his thought pointed toward conclusions about social unity and political authority that would prove influential for later nationalist and socialist movements.\n\nThe tension between these two strands of Rousseauian thought created both creative possibilities and destructive potentials that would shape subsequent intellectual and political history. The emphasis on individual authenticity and natural freedom would contribute to movements for personal liberation, artistic creativity, and resistance to oppressive authority. The emphasis on social unity and collective virtue would contribute to movements for democratic participation, national solidarity, and social transformation.\n\nBut the combination of these emphases would also create new forms of authoritarianism that claimed to represent true freedom while eliminating the conditions necessary for individual autonomy. The idea that individuals could be forced to be free, that those who resisted collective decisions were demonstrating false consciousness rather than legitimate disagreement, and that genuine democracy required the elimination of private interests and partial associations—all these ideas contained potentials for tyranny that would be realized in various revolutionary movements that claimed Rousseauian inspiration.\n\n## The Modern Legacy: Authenticity and Its Discontents\n\nRousseau's influence on modern thinking about individual freedom and authentic self-expression has been so profound that it is difficult to imagine contemporary culture without it. The modern emphasis on being true to oneself, the suspicion of social conventions and institutional authorities, the celebration of individual difference and personal creativity, the assumption that genuine virtue consists in natural sentiment rather than learned discipline—all these characteristic features of modern individualistic culture can be traced back to Rousseauian insights and their Romantic development.\n\nBut this Rousseauian legacy has also created new problems for thinking about individual responsibility and social cooperation. If authenticity is the highest value, how can shared moral standards be maintained? If individual self-expression is intrinsically valuable, how can the social cooperation necessary for complex modern societies be achieved? If natural sentiment is a better guide than reasoned reflection, how can moral and political disagreements be resolved through rational discussion rather than emotional manipulation or physical force?\n\nThese questions have become increasingly pressing as the therapeutic culture that emerged from Rousseauian insights has become more influential in contemporary Western societies. The emphasis on individual self-fulfillment, emotional authenticity, and personal growth has contributed to valuable developments in psychology, education, and social relations. But it has also contributed to forms of narcissism, moral relativism, and social fragmentation that earlier traditions were better equipped to handle.\n\nUnderstanding Rousseau's revolutionary contribution to thinking about human nature and individual freedom is thus crucial for comprehending both the possibilities and the limitations of modern individualistic culture. His insights about the importance of natural development, emotional authenticity, and individual self-expression remain valuable resources for resisting oppressive authority and encouraging human flourishing. But his failure to resolve the tensions between individual autonomy and social authority, between personal authenticity and moral obligation, between natural freedom and political necessity, continues to generate problems that purely individualistic approaches seem unable to address.\n\nThe Rousseauian revolution thus represents both the culmination of earlier Christian and Enlightenment insights about individual dignity and the beginning of new forms of moral and political confusion that would challenge the stability of liberal democratic societies. The tension between the individualistic and collectivistic implications of his thought would continue to shape intellectual and political movements for centuries, generating both creative possibilities for human liberation and destructive potentials for new forms of tyranny that claimed to represent true freedom while eliminating the conditions necessary for genuine individual autonomy.","srcMarkdownNoYaml":""},"formats":{"html":{"identifier":{"display-name":"HTML","target-format":"html","base-format":"html"},"execute":{"fig-width":7,"fig-height":5,"fig-format":"retina","fig-dpi":96,"df-print":"default","error":false,"eval":true,"cache":null,"freeze":false,"echo":true,"output":true,"warning":true,"include":true,"keep-md":false,"keep-ipynb":false,"ipynb":null,"enabled":null,"daemon":null,"daemon-restart":false,"debug":false,"ipynb-filters":[],"ipynb-shell-interactivity":null,"plotly-connected":true,"engine":"markdown"},"render":{"keep-tex":false,"keep-typ":false,"keep-source":false,"keep-hidden":false,"prefer-html":false,"output-divs":true,"output-ext":"html","fig-align":"default","fig-pos":null,"fig-env":null,"code-fold":true,"code-overflow":"scroll","code-link":false,"code-line-numbers":false,"code-tools":false,"tbl-colwidths":"auto","merge-includes":true,"inline-includes":false,"preserve-yaml":false,"latex-auto-mk":true,"latex-auto-install":true,"latex-clean":true,"latex-min-runs":1,"latex-max-runs":10,"latex-makeindex":"makeindex","latex-makeindex-opts":[],"latex-tlmgr-opts":[],"latex-input-paths":[],"latex-output-dir":null,"link-external-icon":false,"link-external-newwindow":false,"self-contained-math":false,"format-resources":[],"notebook-links":true},"pandoc":{"standalone":true,"wrap":"none","default-image-extension":"png","to":"html","reference-location":"block","output-file":"9_rousseau.html"},"language":{"toc-title-document":"Table of contents","toc-title-website":"On this page","related-formats-title":"Other Formats","related-notebooks-title":"Notebooks","source-notebooks-prefix":"Source","other-links-title":"Other Links","code-links-title":"Code Links","launch-dev-container-title":"Launch Dev Container","launch-binder-title":"Launch Binder","article-notebook-label":"Article Notebook","notebook-preview-download":"Download Notebook","notebook-preview-download-src":"Download Source","notebook-preview-back":"Back to Article","manuscript-meca-bundle":"MECA Bundle","section-title-abstract":"Abstract","section-title-appendices":"Appendices","section-title-footnotes":"Footnotes","section-title-references":"References","section-title-reuse":"Reuse","section-title-copyright":"Copyright","section-title-citation":"Citation","appendix-attribution-cite-as":"For attribution, please cite this work as:","appendix-attribution-bibtex":"BibTeX citation:","appendix-view-license":"View License","title-block-author-single":"Author","title-block-author-plural":"Authors","title-block-affiliation-single":"Affiliation","title-block-affiliation-plural":"Affiliations","title-block-published":"Published","title-block-modified":"Modified","title-block-keywords":"Keywords","callout-tip-title":"Tip","callout-note-title":"Note","callout-warning-title":"Warning","callout-important-title":"Important","callout-caution-title":"Caution","code-summary":"Code","code-tools-menu-caption":"Code","code-tools-show-all-code":"Show All Code","code-tools-hide-all-code":"Hide All Code","code-tools-view-source":"View Source","code-tools-source-code":"Source Code","tools-share":"Share","tools-download":"Download","code-line":"Line","code-lines":"Lines","copy-button-tooltip":"Copy to Clipboard","copy-button-tooltip-success":"Copied!","repo-action-links-edit":"Edit this page","repo-action-links-source":"View source","repo-action-links-issue":"Report an issue","back-to-top":"Back to top","search-no-results-text":"No results","search-matching-documents-text":"matching documents","search-copy-link-title":"Copy link to search","search-hide-matches-text":"Hide additional matches","search-more-match-text":"more match in this document","search-more-matches-text":"more matches in this document","search-clear-button-title":"Clear","search-text-placeholder":"","search-detached-cancel-button-title":"Cancel","search-submit-button-title":"Submit","search-label":"Search","toggle-section":"Toggle section","toggle-sidebar":"Toggle sidebar navigation","toggle-dark-mode":"Toggle dark mode","toggle-reader-mode":"Toggle reader mode","toggle-navigation":"Toggle navigation","crossref-fig-title":"Figure","crossref-tbl-title":"Table","crossref-lst-title":"Listing","crossref-thm-title":"Theorem","crossref-lem-title":"Lemma","crossref-cor-title":"Corollary","crossref-prp-title":"Proposition","crossref-cnj-title":"Conjecture","crossref-def-title":"Definition","crossref-exm-title":"Example","crossref-exr-title":"Exercise","crossref-ch-prefix":"Chapter","crossref-apx-prefix":"Appendix","crossref-sec-prefix":"Section","crossref-eq-prefix":"Equation","crossref-lof-title":"List of Figures","crossref-lot-title":"List of Tables","crossref-lol-title":"List of Listings","environment-proof-title":"Proof","environment-remark-title":"Remark","environment-solution-title":"Solution","listing-page-order-by":"Order By","listing-page-order-by-default":"Default","listing-page-order-by-date-asc":"Oldest","listing-page-order-by-date-desc":"Newest","listing-page-order-by-number-desc":"High to Low","listing-page-order-by-number-asc":"Low to High","listing-page-field-date":"Date","listing-page-field-title":"Title","listing-page-field-description":"Description","listing-page-field-author":"Author","listing-page-field-filename":"File Name","listing-page-field-filemodified":"Modified","listing-page-field-subtitle":"Subtitle","listing-page-field-readingtime":"Reading Time","listing-page-field-wordcount":"Word Count","listing-page-field-categories":"Categories","listing-page-minutes-compact":"{0} min","listing-page-category-all":"All","listing-page-no-matches":"No matching items","listing-page-words":"{0} words","listing-page-filter":"Filter","draft":"Draft"},"metadata":{"lang":"en","fig-responsive":true,"quarto-version":"1.6.32","bibliography":["../self.bib"],"citation-location":"document","theme":"cosmo"},"extensions":{"book":{"multiFile":true}}},"pdf":{"identifier":{"display-name":"PDF","target-format":"pdf","base-format":"pdf"},"execute":{"fig-width":5.5,"fig-height":3.5,"fig-format":"pdf","fig-dpi":300,"df-print":"default","error":false,"eval":true,"cache":null,"freeze":false,"echo":true,"output":true,"warning":true,"include":true,"keep-md":false,"keep-ipynb":false,"ipynb":null,"enabled":null,"daemon":null,"daemon-restart":false,"debug":false,"ipynb-filters":[],"ipynb-shell-interactivity":null,"plotly-connected":true,"engine":"markdown"},"render":{"keep-tex":false,"keep-typ":false,"keep-source":false,"keep-hidden":false,"prefer-html":false,"output-divs":true,"output-ext":"pdf","fig-align":"default","fig-pos":null,"fig-env":null,"code-fold":"none","code-overflow":"scroll","code-link":false,"code-line-numbers":false,"code-tools":false,"tbl-colwidths":true,"merge-includes":true,"inline-includes":false,"preserve-yaml":false,"latex-auto-mk":true,"latex-auto-install":true,"latex-clean":true,"latex-min-runs":1,"latex-max-runs":10,"latex-makeindex":"makeindex","latex-makeindex-opts":[],"latex-tlmgr-opts":[],"latex-input-paths":[],"latex-output-dir":null,"link-external-icon":false,"link-external-newwindow":false,"self-contained-math":false,"format-resources":[]},"pandoc":{"pdf-engine":"xelatex","standalone":true,"variables":{"graphics":true,"tables":true},"default-image-extension":"pdf","to":"pdf","reference-location":"block","include-in-header":{"text":"\\usepackage{makeidx}\n\\makeindex\n"},"include-after-body":{"text":"\\printindex\n"},"output-file":"9_rousseau.pdf"},"language":{"toc-title-document":"Table of contents","toc-title-website":"On this page","related-formats-title":"Other Formats","related-notebooks-title":"Notebooks","source-notebooks-prefix":"Source","other-links-title":"Other Links","code-links-title":"Code Links","launch-dev-container-title":"Launch Dev Container","launch-binder-title":"Launch Binder","article-notebook-label":"Article Notebook","notebook-preview-download":"Download Notebook","notebook-preview-download-src":"Download Source","notebook-preview-back":"Back to Article","manuscript-meca-bundle":"MECA Bundle","section-title-abstract":"Abstract","section-title-appendices":"Appendices","section-title-footnotes":"Footnotes","section-title-references":"References","section-title-reuse":"Reuse","section-title-copyright":"Copyright","section-title-citation":"Citation","appendix-attribution-cite-as":"For attribution, please cite this work as:","appendix-attribution-bibtex":"BibTeX citation:","appendix-view-license":"View License","title-block-author-single":"Author","title-block-author-plural":"Authors","title-block-affiliation-single":"Affiliation","title-block-affiliation-plural":"Affiliations","title-block-published":"Published","title-block-modified":"Modified","title-block-keywords":"Keywords","callout-tip-title":"Tip","callout-note-title":"Note","callout-warning-title":"Warning","callout-important-title":"Important","callout-caution-title":"Caution","code-summary":"Code","code-tools-menu-caption":"Code","code-tools-show-all-code":"Show All Code","code-tools-hide-all-code":"Hide All Code","code-tools-view-source":"View Source","code-tools-source-code":"Source Code","tools-share":"Share","tools-download":"Download","code-line":"Line","code-lines":"Lines","copy-button-tooltip":"Copy to Clipboard","copy-button-tooltip-success":"Copied!","repo-action-links-edit":"Edit this page","repo-action-links-source":"View source","repo-action-links-issue":"Report an issue","back-to-top":"Back to top","search-no-results-text":"No results","search-matching-documents-text":"matching documents","search-copy-link-title":"Copy link to search","search-hide-matches-text":"Hide additional matches","search-more-match-text":"more match in this document","search-more-matches-text":"more matches in this document","search-clear-button-title":"Clear","search-text-placeholder":"","search-detached-cancel-button-title":"Cancel","search-submit-button-title":"Submit","search-label":"Search","toggle-section":"Toggle section","toggle-sidebar":"Toggle sidebar navigation","toggle-dark-mode":"Toggle dark mode","toggle-reader-mode":"Toggle reader mode","toggle-navigation":"Toggle navigation","crossref-fig-title":"Figure","crossref-tbl-title":"Table","crossref-lst-title":"Listing","crossref-thm-title":"Theorem","crossref-lem-title":"Lemma","crossref-cor-title":"Corollary","crossref-prp-title":"Proposition","crossref-cnj-title":"Conjecture","crossref-def-title":"Definition","crossref-exm-title":"Example","crossref-exr-title":"Exercise","crossref-ch-prefix":"Chapter","crossref-apx-prefix":"Appendix","crossref-sec-prefix":"Section","crossref-eq-prefix":"Equation","crossref-lof-title":"List of Figures","crossref-lot-title":"List of Tables","crossref-lol-title":"List of Listings","environment-proof-title":"Proof","environment-remark-title":"Remark","environment-solution-title":"Solution","listing-page-order-by":"Order By","listing-page-order-by-default":"Default","listing-page-order-by-date-asc":"Oldest","listing-page-order-by-date-desc":"Newest","listing-page-order-by-number-desc":"High to Low","listing-page-order-by-number-asc":"Low to High","listing-page-field-date":"Date","listing-page-field-title":"Title","listing-page-field-description":"Description","listing-page-field-author":"Author","listing-page-field-filename":"File Name","listing-page-field-filemodified":"Modified","listing-page-field-subtitle":"Subtitle","listing-page-field-readingtime":"Reading Time","listing-page-field-wordcount":"Word Count","listing-page-field-categories":"Categories","listing-page-minutes-compact":"{0} min","listing-page-category-all":"All","listing-page-no-matches":"No matching items","listing-page-words":"{0} words","listing-page-filter":"Filter","draft":"Draft"},"metadata":{"block-headings":true,"bibliography":["../self.bib"],"citation-location":"document","documentclass":"scrbook","fontfamily":"Alegreya","geometry":"paperwidth=5.5in, paperheight=8.5in, margin=0.8in","code":false},"extensions":{"book":{"selfContainedOutput":true}}}},"projectFormats":["html","pdf"]}